toriicli/__init__.py
toriicli/__main__.py
toriicli/config.py
toriicli/example_config.yml
toriicli/nuget.config
toriicli/nuget.py
toriicli/packages.config
toriicli/build/__init__.py
toriicli/build/build_data.py
toriicli/build/build_def.py
toriicli/build/detect_unity.py
toriicli/build/unity.py
toriicli/steps/__init__.py
toriicli/steps/base_step.py
toriicli/steps/butler_step.py
toriicli/steps/chmod_step.py
toriicli/steps/compress_step.py
toriicli/steps/export_step.py
toriicli/steps/factory.py
toriicli/steps/import_step.py
toriicli/steps/schemas.py
toriicli/storage/__init__.py
toriicli/storage/local_provider.py
toriicli/storage/provider.py
toriicli/storage/s3_provider.py
toriicli-0.0.10.dist-info/LICENSE
toriicli-0.0.10.dist-info/METADATA
toriicli-0.0.10.dist-info/WHEEL
toriicli-0.0.10.dist-info/entry_points.txt
toriicli-0.0.10.dist-info/top_level.txt
toriicli-0.0.10.dist-info/RECORD
