Metadata-Version: 2.1
Name: toriicli
Version: 0.0.10
Summary: CLI utility for Torii
Home-page: UNKNOWN
Author: Figglewatts
Author-email: me@figglewatts.co.uk
License: UNKNOWN
Platform: UNKNOWN
Requires-Python: >=3.7
Requires-Dist: pyyaml (>=5.3.1)
Requires-Dist: marshmallow (>=3.6.0)
Requires-Dist: click (>=7.1.2)
Requires-Dist: python-dotenv (>=0.13.0)
Requires-Dist: boto3 (>=1.13.16)
Requires-Dist: jinja2 (>=2.11.2)
Requires-Dist: pefile (>=2019.4.18)
Requires-Dist: xmltodict (>=0.12.0)
